turboml_installer/__init__.py
turboml_installer/colab.py
turboml_installer-0.0.13.dist-info/METADATA
turboml_installer-0.0.13.dist-info/WHEEL
turboml_installer-0.0.13.dist-info/RECORD
