Metadata-Version: 2.3
Name: turboml-installer
Version: 0.0.13
Summary: 
Author: turboml
Author-email: contact@turboml.com
Requires-Python: >=3.11,<3.12
Classifier: Programming Language :: Python :: 3
Classifier: Programming Language :: Python :: 3.11
Requires-Dist: ipython (<=8.31.0)
Requires-Dist: requests (>=2.32.3,<3.0.0)
